crossmapy/__init__.py
crossmapy/_base.py
crossmapy/ccm.py
crossmapy/cmc.py
crossmapy/cme.py
crossmapy/dataset.py
crossmapy/embed.py
crossmapy/gc.py
crossmapy/mi.py
crossmapy/plot.py
crossmapy/te.py
crossmapy/utils.py
crossmapy-0.0.1.dist-info/LICENSE
crossmapy-0.0.1.dist-info/METADATA
crossmapy-0.0.1.dist-info/WHEEL
crossmapy-0.0.1.dist-info/top_level.txt
crossmapy-0.0.1.dist-info/RECORD
