Metadata-Version: 2.1
Name: crossmapy
Version: 0.0.1
Summary: causal inference under dynamical causality framework
Home-page: https://github.com/PengTao-HUST/crossmapy
Author: Peng Tao
Author-email: taopeng543@gmail.com
License: MIT Licence
Platform: UNKNOWN
Classifier: Programming Language :: Python :: 3
Classifier: License :: OSI Approved :: MIT License
Requires-Python: >=3.6
Requires-Dist: scipy
Requires-Dist: scikit-learn
Requires-Dist: networkx
Requires-Dist: numba
Requires-Dist: seaborn
Requires-Dist: matplotlib
Requires-Dist: numpy
